setup.py
SherlockDistribution/Binomialdistribution.py
SherlockDistribution/Gaussiandistribution.py
SherlockDistribution/Generaldistribution.py
SherlockDistribution/__init__.py
SherlockDistribution.egg-info/PKG-INFO
SherlockDistribution.egg-info/SOURCES.txt
SherlockDistribution.egg-info/dependency_links.txt
SherlockDistribution.egg-info/not-zip-safe
SherlockDistribution.egg-info/requires.txt
SherlockDistribution.egg-info/top_level.txt