Metadata-Version: 1.2
Name: SherlockDistribution
Version: 1.1
Summary: Gaussian and Binomial distributions
Home-page: UNKNOWN
Author: Swapnil Jha
Author-email: swapniljha001@gmail.com
License: UNKNOWN
Project-URL: Author LinkedIn, https://www.linkedin.com/in/swapniljha001
Platform: UNKNOWN
